{"is_offline": true, "global_note": "Hallo Welt!", "beta_token": "5ae2caf-4f22c4a-c29896-7e50dc", "label": "&pi;-Learn", "offline_note": "## Private Beta\n\nHerzlich Willkommen bei **&pi;-Learn**.\n\nDiese Webseite befindet sich im Moment in einer privaten Beta und kann nur von eingeladenen Benutzern benutzt werden.\n\nWir werden diese Seite bald f\u00fcr die Allgemeinheit zug\u00e4nglich machen, bis dahin ben\u00f6tigen Sie noch etwas Geduld.\n\n*Das &pi;-Learn Team*", "in_beta": true, "mathjax": true, "register_key": "covfefe"}